LICENSE
MANIFEST.in
ORIGINAL-README
README.rst
c.tgz
get_source_files.py
pyzk_docstrings.h
setup.py
source-release-instructions.txt
zookeeper.c
zookeeper_344.patch
zookeeper_patched_344.c
src/zookeepertests/__init__.py
src/zookeepertests/acl_test.py
src/zookeepertests/async_test.py
src/zookeepertests/callback_test.py
src/zookeepertests/clientid_test.py
src/zookeepertests/close_deadlock_test.py
src/zookeepertests/connection_test.py
src/zookeepertests/create_test.py
src/zookeepertests/delete_test.py
src/zookeepertests/exists_test.py
src/zookeepertests/get_set_test.py
src/zookeepertests/run_tests.sh
src/zookeepertests/zkServer.sh
src/zookeepertests/zktestbase.py
zc_zookeeper_static.egg-info/PKG-INFO
zc_zookeeper_static.egg-info/SOURCES.txt
zc_zookeeper_static.egg-info/dependency_links.txt
zc_zookeeper_static.egg-info/top_level.txt