Metadata-Version: 1.0
Name: zc-zookeeper-static
Version: 3.4.4
Summary: ZooKeeper Python bindings
Home-page: http://pypi.python.org/pypi/zc-zookeeper-static
Author: Henry Robinson
Author-email: henry@cloudera.com
License: Apache
Platform: UNKNOWN
